{
  "Version": "2012-10-17",
  "Statement": [
    {
      "Sid": "ECRAccess",
      "Effect": "Allow",
      "Action": [
        "ecr:GetAuthorizationToken",
        "ecr:BatchCheckLayerAvailability",
        "ecr:GetDownloadUrlForLayer",
        "ecr:BatchGetImage",
        "ecr:PutImage",
        "ecr:InitiateLayerUpload",
        "ecr:UploadLayerPart",
        "ecr:CompleteLayerUpload"
      ],
      "Resource": "*"
    },
    {
      "Sid": "ECSDeployment",
      "Effect": "Allow",
      "Action": [
        "ecs:DescribeServices",
        "ecs:DescribeTaskDefinition",
        "ecs:DescribeTasks",
        "ecs:ListTasks",
        "ecs:RegisterTaskDefinition",
        "ecs:UpdateService"
      ],
      "Resource": "*",
      "Condition": {
        "StringLike": {
          "ecs:cluster": "*jwt-module-*"
        }
      }
    },
    {
      "Sid": "PassRole",
      "Effect": "Allow",
      "Action": "iam:PassRole",
      "Resource": "arn:aws:iam::*:role/jwt-module-*",
      "Condition": {
        "StringEquals": {
          "iam:PassedToService": "ecs-tasks.amazonaws.com"
        }
      }
    },
    {
      "Sid": "ELBDescribe",
      "Effect": "Allow",
      "Action": [
        "elasticloadbalancing:DescribeLoadBalancers",
        "elasticloadbalancing:DescribeTargetGroups",
        "elasticloadbalancing:DescribeTargetHealth"
      ],
      "Resource": "*"
    }
  ]
}
